vkale/__init__.py
vkale/common.py
vkale/enums.py
vkale/method.py
vkale/vk.py
vkale/items/__init__.py
vkale/items/callback.py
vkale/items/friends_items.py
vkale/items/item.py
vkale/items/user_items.py
vkale/items/wall_items.py
vkale/methods/__init__.py
vkale/methods/friends.py
vkale/methods/groups.py
vkale/methods/messages.py
vkale/methods/users.py
vkale/methods/wall.py
vkale/test/__init__.py
vkale/test/test_basic.py
vkale/test/test_data.py
vkale/test/test_vk.py
vkale/test/test_webhook.py
vkale/tools/__init__.py
vkale/tools/auth_flow.py
vkale/tools/auth_flow_console.py
vkale-0.4.2.dist-info/METADATA
vkale-0.4.2.dist-info/WHEEL
vkale-0.4.2.dist-info/top_level.txt
vkale-0.4.2.dist-info/RECORD
