Metadata-Version: 2.1
Name: vkale
Version: 0.4.2
Summary: API for VK
Home-page: UNKNOWN
Author: Smyek
Author-email: smyek.job@gmail.com
License: MIT
Platform: UNKNOWN
Requires-Dist: requests
Requires-Dist: ratelimit
